{
  "event_name": "UFC Fight Night: Della Maddalena vs. Prates",
  "event_slug": "UFC_Fight_Night_Della_Maddalena_vs._Prates",
  "event_date": "May 02, 2026",
  "location": "Perth, Western Australia, Australia",
  "generated_at": "2026-05-16T00:15:21.083190",
  "model_stats": {
    "accuracy": 82.6,
    "roc_auc": 0.9229,
    "high_conf_acc": 89.7,
    "overfit_gap": 0.026
  },
  "summary": {
    "total_fights": 13,
    "high_conf": 4,
    "medium_conf": 3,
    "low_conf": 6,
    "not_found": 0,
    "ev_plays": 0
  },
  "fights": [
    {
      "fighter_a": "Carlos Prates",
      "fighter_b": "Jack Della Maddalena",
      "prob_a": 87.1,
      "prob_b": 12.9,
      "winner": "Carlos Prates",
      "winner_prob": 87.1,
      "confidence": "high",
      "elo_a": 1572.8,
      "elo_b": 1644.3,
      "elo_diff": -71.6,
      "style_a": "hybrid",
      "style_b": "striker",
      "chaos": 0.498,
      "elo_clash": true,
      "title_fight": false,
      "odds_a": null,
      "odds_b": null,
      "ev_a": null,
      "ev_b": null,
      "edge_a": null,
      "edge_b": null,
      "vegas_prob_a": null,
      "vegas_prob_b": null,
      "weight_class": "Welterweight",
      "not_found": false,
      "actual_winner": "Carlos Prates",
      "result": "correct"
    },
    {
      "fighter_a": "Quillan Salkilld",
      "fighter_b": "Beneil Dariush",
      "prob_a": 47.4,
      "prob_b": 52.6,
      "winner": "Beneil Dariush",
      "winner_prob": 52.6,
      "confidence": "low",
      "elo_a": 1532.2,
      "elo_b": 1642.3,
      "elo_diff": -110.1,
      "style_a": "wrestler",
      "style_b": "hybrid",
      "chaos": 0.514,
      "elo_clash": false,
      "title_fight": false,
      "odds_a": null,
      "odds_b": null,
      "ev_a": null,
      "ev_b": null,
      "edge_a": null,
      "edge_b": null,
      "vegas_prob_a": null,
      "vegas_prob_b": null,
      "weight_class": "Lightweight",
      "not_found": false,
      "actual_winner": "Quillan Salkilld",
      "result": "wrong"
    },
    {
      "fighter_a": "Steve Erceg",
      "fighter_b": "Tim Elliott",
      "prob_a": 13.2,
      "prob_b": 86.8,
      "winner": "Tim Elliott",
      "winner_prob": 86.8,
      "confidence": "high",
      "elo_a": 1516.1,
      "elo_b": 1521.1,
      "elo_diff": -5.0,
      "style_a": "hybrid",
      "style_b": "grappler",
      "chaos": 0.538,
      "elo_clash": false,
      "title_fight": false,
      "odds_a": null,
      "odds_b": null,
      "ev_a": null,
      "ev_b": null,
      "edge_a": null,
      "edge_b": null,
      "vegas_prob_a": null,
      "vegas_prob_b": null,
      "weight_class": "Flyweight",
      "not_found": false,
      "actual_winner": "Steve Erceg",
      "result": "wrong"
    },
    {
      "fighter_a": "Marwan Rahiki",
      "fighter_b": "Ollie Schmid",
      "prob_a": 50.0,
      "prob_b": 50.0,
      "winner": "Marwan Rahiki",
      "winner_prob": 50.0,
      "confidence": "low",
      "elo_a": 1500.0,
      "elo_b": 1500.0,
      "elo_diff": 0.0,
      "style_a": "unknown",
      "style_b": "unknown",
      "chaos": 0.5,
      "elo_clash": false,
      "title_fight": false,
      "data_limited": true,
      "odds_a": null,
      "odds_b": null,
      "ev_a": null,
      "ev_b": null,
      "edge_a": null,
      "edge_b": null,
      "vegas_prob_a": null,
      "vegas_prob_b": null,
      "weight_class": "Featherweight",
      "not_found": false
    },
    {
      "fighter_a": "Brando Pericic",
      "fighter_b": "Shamil Gaziev",
      "prob_a": 45.1,
      "prob_b": 54.9,
      "winner": "Shamil Gaziev",
      "winner_prob": 54.9,
      "confidence": "medium",
      "elo_a": 1500.0,
      "elo_b": 1534.4,
      "elo_diff": -34.4,
      "style_a": "unknown",
      "style_b": "unknown",
      "chaos": 0.5,
      "elo_clash": false,
      "title_fight": false,
      "data_limited": true,
      "odds_a": null,
      "odds_b": null,
      "ev_a": null,
      "ev_b": null,
      "edge_a": null,
      "edge_b": null,
      "vegas_prob_a": null,
      "vegas_prob_b": null,
      "weight_class": "Heavyweight",
      "not_found": false
    },
    {
      "fighter_a": "Louie Sutherland",
      "fighter_b": "Tai Tuivasa",
      "prob_a": 48.9,
      "prob_b": 51.1,
      "winner": "Tai Tuivasa",
      "winner_prob": 51.1,
      "confidence": "low",
      "elo_a": 1500.0,
      "elo_b": 1507.7,
      "elo_diff": -7.7,
      "style_a": "unknown",
      "style_b": "unknown",
      "chaos": 0.5,
      "elo_clash": false,
      "title_fight": false,
      "data_limited": true,
      "odds_a": null,
      "odds_b": null,
      "ev_a": null,
      "ev_b": null,
      "edge_a": null,
      "edge_b": null,
      "vegas_prob_a": null,
      "vegas_prob_b": null,
      "weight_class": "Heavyweight",
      "not_found": false
    },
    {
      "fighter_a": "Cam Rowston",
      "fighter_b": "Robert Bryczek",
      "prob_a": 49.7,
      "prob_b": 50.3,
      "winner": "Robert Bryczek",
      "winner_prob": 50.3,
      "confidence": "low",
      "elo_a": 1500.0,
      "elo_b": 1502.4,
      "elo_diff": -2.4,
      "style_a": "unknown",
      "style_b": "unknown",
      "chaos": 0.5,
      "elo_clash": false,
      "title_fight": false,
      "data_limited": true,
      "odds_a": null,
      "odds_b": null,
      "ev_a": null,
      "ev_b": null,
      "edge_a": null,
      "edge_b": null,
      "vegas_prob_a": null,
      "vegas_prob_b": null,
      "weight_class": "Middleweight",
      "not_found": false
    },
    {
      "fighter_a": "Junior Tafa",
      "fighter_b": "Kevin Christian",
      "prob_a": 46.0,
      "prob_b": 54.0,
      "winner": "Kevin Christian",
      "winner_prob": 54.0,
      "confidence": "medium",
      "elo_a": 1472.0,
      "elo_b": 1500.0,
      "elo_diff": -28.0,
      "style_a": "unknown",
      "style_b": "unknown",
      "chaos": 0.5,
      "elo_clash": false,
      "title_fight": false,
      "data_limited": true,
      "odds_a": null,
      "odds_b": null,
      "ev_a": null,
      "ev_b": null,
      "edge_a": null,
      "edge_b": null,
      "vegas_prob_a": null,
      "vegas_prob_b": null,
      "weight_class": "Light Heavyweight",
      "not_found": false
    },
    {
      "fighter_a": "Jacob Malkoun",
      "fighter_b": "Gerald Meerschaert",
      "prob_a": 90.0,
      "prob_b": 10.0,
      "winner": "Jacob Malkoun",
      "winner_prob": 90.0,
      "confidence": "high",
      "elo_a": 1520.1,
      "elo_b": 1496.4,
      "elo_diff": 23.6,
      "style_a": "wrestler",
      "style_b": "hybrid",
      "chaos": 0.468,
      "elo_clash": false,
      "title_fight": false,
      "odds_a": null,
      "odds_b": null,
      "ev_a": null,
      "ev_b": null,
      "edge_a": null,
      "edge_b": null,
      "vegas_prob_a": null,
      "vegas_prob_b": null,
      "weight_class": "Middleweight",
      "not_found": false,
      "actual_winner": "Jacob Malkoun",
      "result": "correct"
    },
    {
      "fighter_a": "Colby Thicknesse",
      "fighter_b": "Vince Morales",
      "prob_a": 9.4,
      "prob_b": 90.6,
      "winner": "Vince Morales",
      "winner_prob": 90.6,
      "confidence": "high",
      "elo_a": 1484.0,
      "elo_b": 1437.2,
      "elo_diff": 46.8,
      "style_a": "hybrid",
      "style_b": "hybrid",
      "chaos": 0.5,
      "elo_clash": false,
      "title_fight": false,
      "odds_a": null,
      "odds_b": null,
      "ev_a": null,
      "ev_b": null,
      "edge_a": null,
      "edge_b": null,
      "vegas_prob_a": null,
      "vegas_prob_b": null,
      "weight_class": "Bantamweight",
      "not_found": false,
      "actual_winner": "Colby Thicknesse",
      "result": "wrong"
    },
    {
      "fighter_a": "Wes Schultz",
      "fighter_b": "Ben Johnston",
      "prob_a": 50.0,
      "prob_b": 50.0,
      "winner": "Wes Schultz",
      "winner_prob": 50.0,
      "confidence": "low",
      "elo_a": 1500.0,
      "elo_b": 1500.0,
      "elo_diff": 0.0,
      "style_a": "unknown",
      "style_b": "unknown",
      "chaos": 0.5,
      "elo_clash": false,
      "title_fight": false,
      "data_limited": true,
      "odds_a": null,
      "odds_b": null,
      "ev_a": null,
      "ev_b": null,
      "edge_a": null,
      "edge_b": null,
      "vegas_prob_a": null,
      "vegas_prob_b": null,
      "weight_class": "Middleweight",
      "not_found": false
    },
    {
      "fighter_a": "Jonathan Micallef",
      "fighter_b": "Themba Gorimbo",
      "prob_a": 58.5,
      "prob_b": 41.5,
      "winner": "Jonathan Micallef",
      "winner_prob": 58.5,
      "confidence": "medium",
      "elo_a": 1516.8,
      "elo_b": 1533.6,
      "elo_diff": -16.8,
      "style_a": "hybrid",
      "style_b": "grappler",
      "chaos": 0.5,
      "elo_clash": false,
      "title_fight": false,
      "odds_a": null,
      "odds_b": null,
      "ev_a": null,
      "ev_b": null,
      "edge_a": null,
      "edge_b": null,
      "vegas_prob_a": null,
      "vegas_prob_b": null,
      "weight_class": "Welterweight",
      "not_found": false,
      "actual_winner": "Jonathan Micallef",
      "result": "correct"
    },
    {
      "fighter_a": "Kody Steele",
      "fighter_b": "Dom Mar Fan",
      "prob_a": 47.5,
      "prob_b": 52.5,
      "winner": "Dom Mar Fan",
      "winner_prob": 52.5,
      "confidence": "low",
      "elo_a": 1482.6,
      "elo_b": 1500.0,
      "elo_diff": -17.4,
      "style_a": "unknown",
      "style_b": "unknown",
      "chaos": 0.5,
      "elo_clash": false,
      "title_fight": false,
      "data_limited": true,
      "odds_a": null,
      "odds_b": null,
      "ev_a": null,
      "ev_b": null,
      "edge_a": null,
      "edge_b": null,
      "vegas_prob_a": null,
      "vegas_prob_b": null,
      "weight_class": "Lightweight",
      "not_found": false
    }
  ],
  "ev_plays": [],
  "parlays": {
    "high_only": {
      "legs": [],
      "prob": 100.0,
      "count": 0
    },
    "high_and_med": {
      "legs": [
        {
          "fighter": "Tim Elliott",
          "prob": 86.8
        },
        {
          "fighter": "Jacob Malkoun",
          "prob": 90.0
        },
        {
          "fighter": "Vince Morales",
          "prob": 90.6
        }
      ],
      "prob": 70.8,
      "count": 3
    }
  }
}